MANIFEST.in
README.rst
example_filter.py
example_optimization.py
gradcheck.py
joint_bilateral_filter_layer.py
setup.py
csrc/jbf_layer_cpu_backward.cpp
csrc/jbf_layer_cpu_forward.cpp
csrc/jbf_layer_gpu_backward.cu
csrc/jbf_layer_gpu_forward.cu
csrc/jointbilateral.h
csrc/jointbilateralfilter_cpu.cpp
csrc/jointbilateralfilter_gpu.cu
jointbilateralfilter_torch.egg-info/PKG-INFO
jointbilateralfilter_torch.egg-info/SOURCES.txt
jointbilateralfilter_torch.egg-info/dependency_links.txt
jointbilateralfilter_torch.egg-info/top_level.txt
utils/common_utils.h
utils/cuda_error_check.h
utils/meta_macros.h
utils/resample_utils.h
utils/tensor_description.h