Metadata-Version: 2.1
Name: jointbilateralfilter-torch
Version: 1.0.0
Summary: Trainable Joint Bilateral Filter Layer (PyTorch)
Home-page: https://github.com/faebstn96/trainable-joint-bilateral-filter-source
Author: Fabian Wagner
Author-email: fabian.wagner@fau.de
License: UNKNOWN
Platform: UNKNOWN
